odoo/addons/stock_picking_report_incoming_delivery_address/README.rst
odoo/addons/stock_picking_report_incoming_delivery_address/__init__.py
odoo/addons/stock_picking_report_incoming_delivery_address/__manifest__.py
odoo/addons/stock_picking_report_incoming_delivery_address/i18n/ca.po
odoo/addons/stock_picking_report_incoming_delivery_address/i18n/ca_ES.po
odoo/addons/stock_picking_report_incoming_delivery_address/i18n/es.po
odoo/addons/stock_picking_report_incoming_delivery_address/i18n/it.po
odoo/addons/stock_picking_report_incoming_delivery_address/i18n/stock_picking_report_incoming_delivery_address.pot
odoo/addons/stock_picking_report_incoming_delivery_address/models/__init__.py
odoo/addons/stock_picking_report_incoming_delivery_address/models/stock_picking_type.py
odoo/addons/stock_picking_report_incoming_delivery_address/readme/CONFIGURE.md
odoo/addons/stock_picking_report_incoming_delivery_address/readme/CONTEXT.md
odoo/addons/stock_picking_report_incoming_delivery_address/readme/CONTRIBUTORS.md
odoo/addons/stock_picking_report_incoming_delivery_address/readme/DESCRIPTION.md
odoo/addons/stock_picking_report_incoming_delivery_address/readme/USAGE.md
odoo/addons/stock_picking_report_incoming_delivery_address/static/description/icon.png
odoo/addons/stock_picking_report_incoming_delivery_address/static/description/index.html
odoo/addons/stock_picking_report_incoming_delivery_address/tests/__init__.py
odoo/addons/stock_picking_report_incoming_delivery_address/tests/test_report_incoming_delivery_address.py
odoo/addons/stock_picking_report_incoming_delivery_address/views/report_deliveryslip.xml
odoo/addons/stock_picking_report_incoming_delivery_address/views/report_stockpicking_operations.xml
odoo/addons/stock_picking_report_incoming_delivery_address/views/stock_picking_type.xml
odoo_addon_stock_picking_report_incoming_delivery_address-16.0.1.0.1.5.dist-info/METADATA
odoo_addon_stock_picking_report_incoming_delivery_address-16.0.1.0.1.5.dist-info/WHEEL
odoo_addon_stock_picking_report_incoming_delivery_address-16.0.1.0.1.5.dist-info/top_level.txt
odoo_addon_stock_picking_report_incoming_delivery_address-16.0.1.0.1.5.dist-info/RECORD
